finbright/__init__.py
finbright/main.py
finbright-0.0.1.dist-info/METADATA
finbright-0.0.1.dist-info/WHEEL
finbright-0.0.1.dist-info/licenses/LICENSE
finbright-0.0.1.dist-info/RECORD
